flask_brython/__init__.py
flask_brython/static/js/brython.min.js
flask_brython/static/js/brython_stdlib.min.js
Flask_Brython-1.0.0.dist-info/LICENSE
Flask_Brython-1.0.0.dist-info/METADATA
Flask_Brython-1.0.0.dist-info/WHEEL
Flask_Brython-1.0.0.dist-info/top_level.txt
Flask_Brython-1.0.0.dist-info/RECORD
