Metadata-Version: 2.1
Name: Flask-Brython
Version: 1.0.0
Summary: This is Brython on flask.
Home-page: https://github.com/lrsgzs/flask-brython
Author: LRS
Author-email: liurongshuo2022@outlook.com
License: MIT
Keywords: flask extension lrspackages
Platform: UNKNOWN
Classifier: License :: OSI Approved :: MIT License
Classifier: Programming Language :: Python
Classifier: Programming Language :: Python :: 3
Classifier: Programming Language :: Python :: 3.7
Classifier: Programming Language :: Python :: Implementation :: CPython
Classifier: Programming Language :: Python :: Implementation :: PyPy
License-File: LICENSE
Requires-Dist: flask
